<?xml version="1.0" encoding="utf-8"?>
<ArrayOfDataStruct xmlns:xsi="http://www.w3.org/2001/XMLSchema-instance" xmlns:xsd="http://www.w3.org/2001/XMLSchema">
  <DataStruct>
    <counter>0</counter>
    <JPNText>随分ぼーっとしてるな</JPNText>
    <TransText />
    <SpeakerName>レフィ</SpeakerName>
    <IsNewLine>false</IsNewLine>
    <Notes />
  </DataStruct>
  <DataStruct>
    <counter>1</counter>
    <JPNText>今日は僕を驚かせないんですか？</JPNText>
    <TransText />
    <SpeakerName>ユウ</SpeakerName>
    <IsNewLine>false</IsNewLine>
    <Notes />
  </DataStruct>
  <DataStruct>
    <counter>2</counter>
    <JPNText>何か一生懸命考えてるみたいだったからさ。</JPNText>
    <TransText />
    <SpeakerName>レフィ</SpeakerName>
    <IsNewLine>true</IsNewLine>
    <Notes />
  </DataStruct>
  <DataStruct>
    <counter>2</counter>
    <JPNText>何か一生懸命考えてるみたいだったからさ。</JPNText>
    <TransText />
    <SpeakerName>レフィ</SpeakerName>
    <IsNewLine>true</IsNewLine>
    <Notes />
  </DataStruct>
  <DataStruct>
    <counter>3</counter>
    <JPNText>少し考え事をしていました</JPNText>
    <TransText />
    <SpeakerName>ユウ</SpeakerName>
    <IsNewLine>false</IsNewLine>
    <Notes />
  </DataStruct>
  <DataStruct>
    <counter>4</counter>
    <JPNText>何考えてたんだよ</JPNText>
    <TransText />
    <SpeakerName>レフィ</SpeakerName>
    <IsNewLine>false</IsNewLine>
    <Notes />
  </DataStruct>
  <DataStruct>
    <counter>5</counter>
    <JPNText>…僕は、間違うことのできない</JPNText>
    <TransText />
    <SpeakerName>ユウ</SpeakerName>
    <IsNewLine>true</IsNewLine>
    <Notes />
  </DataStruct>
  <DataStruct>
    <counter>5</counter>
    <JPNText>…僕は、間違うことのできない</JPNText>
    <TransText />
    <SpeakerName>ユウ</SpeakerName>
    <IsNewLine>true</IsNewLine>
    <Notes />
  </DataStruct>
  <DataStruct>
    <counter>6</counter>
    <JPNText>そして、信じてきたんです…</JPNText>
    <TransText />
    <SpeakerName>ユウ</SpeakerName>
    <IsNewLine>true</IsNewLine>
    <Notes />
  </DataStruct>
  <DataStruct>
    <counter>6</counter>
    <JPNText>そして、信じてきたんです…</JPNText>
    <TransText />
    <SpeakerName>ユウ</SpeakerName>
    <IsNewLine>true</IsNewLine>
    <Notes />
  </DataStruct>
  <DataStruct>
    <counter>7</counter>
    <JPNText>……</JPNText>
    <TransText />
    <SpeakerName>レフィ</SpeakerName>
    <IsNewLine>false</IsNewLine>
    <Notes />
  </DataStruct>
  <DataStruct>
    <counter>8</counter>
    <JPNText>でも、正しさだけが</JPNText>
    <TransText />
    <SpeakerName>ユウ</SpeakerName>
    <IsNewLine>true</IsNewLine>
    <Notes />
  </DataStruct>
  <DataStruct>
    <counter>8</counter>
    <JPNText>でも、正しさだけが</JPNText>
    <TransText />
    <SpeakerName>ユウ</SpeakerName>
    <IsNewLine>true</IsNewLine>
    <Notes />
  </DataStruct>
  <DataStruct>
    <counter>9</counter>
    <JPNText>どういうことだ？</JPNText>
    <TransText />
    <SpeakerName>レフィ</SpeakerName>
    <IsNewLine>false</IsNewLine>
    <Notes />
  </DataStruct>
  <DataStruct>
    <counter>10</counter>
    <JPNText>この戦いを通して、初めて知ることが</JPNText>
    <TransText />
    <SpeakerName>ユウ</SpeakerName>
    <IsNewLine>true</IsNewLine>
    <Notes />
  </DataStruct>
  <DataStruct>
    <counter>10</counter>
    <JPNText>この戦いを通して、初めて知ることが</JPNText>
    <TransText />
    <SpeakerName>ユウ</SpeakerName>
    <IsNewLine>true</IsNewLine>
    <Notes />
  </DataStruct>
  <DataStruct>
    <counter>11</counter>
    <JPNText>真実を明かすことが</JPNText>
    <TransText />
    <SpeakerName>レフィ</SpeakerName>
    <IsNewLine>true</IsNewLine>
    <Notes />
  </DataStruct>
  <DataStruct>
    <counter>11</counter>
    <JPNText>真実を明かすことが</JPNText>
    <TransText />
    <SpeakerName>レフィ</SpeakerName>
    <IsNewLine>true</IsNewLine>
    <Notes />
  </DataStruct>
  <DataStruct>
    <counter>12</counter>
    <JPNText>……</JPNText>
    <TransText />
    <SpeakerName>ユウ</SpeakerName>
    <IsNewLine>true</IsNewLine>
    <Notes />
  </DataStruct>
  <DataStruct>
    <counter>12</counter>
    <JPNText>……</JPNText>
    <TransText />
    <SpeakerName>ユウ</SpeakerName>
    <IsNewLine>true</IsNewLine>
    <Notes />
  </DataStruct>
  <DataStruct>
    <counter>13</counter>
    <JPNText>でも…僕は謎が好きなんです。</JPNText>
    <TransText />
    <SpeakerName>ユウ</SpeakerName>
    <IsNewLine>true</IsNewLine>
    <Notes />
  </DataStruct>
  <DataStruct>
    <counter>13</counter>
    <JPNText>でも…僕は謎が好きなんです。</JPNText>
    <TransText />
    <SpeakerName>ユウ</SpeakerName>
    <IsNewLine>true</IsNewLine>
    <Notes />
  </DataStruct>
  <DataStruct>
    <counter>14</counter>
    <JPNText>謎が好き？</JPNText>
    <TransText />
    <SpeakerName>レフィ</SpeakerName>
    <IsNewLine>false</IsNewLine>
    <Notes />
  </DataStruct>
  <DataStruct>
    <counter>15</counter>
    <JPNText>レフィさん…あなたはどうですか？</JPNText>
    <TransText />
    <SpeakerName>ユウ</SpeakerName>
    <IsNewLine>true</IsNewLine>
    <Notes />
  </DataStruct>
  <DataStruct>
    <counter>15</counter>
    <JPNText>レフィさん…あなたはどうですか？</JPNText>
    <TransText />
    <SpeakerName>ユウ</SpeakerName>
    <IsNewLine>true</IsNewLine>
    <Notes />
  </DataStruct>
  <DataStruct>
    <counter>16</counter>
    <JPNText>そんな表層的なことではありませんよ</JPNText>
    <TransText />
    <SpeakerName>ユウ</SpeakerName>
    <IsNewLine>false</IsNewLine>
    <Notes />
  </DataStruct>
  <DataStruct>
    <counter>17</counter>
    <JPNText>そうなのか？　でもユウが『ずばり！』って</JPNText>
    <TransText />
    <SpeakerName>レフィ</SpeakerName>
    <IsNewLine>true</IsNewLine>
    <Notes />
  </DataStruct>
  <DataStruct>
    <counter>17</counter>
    <JPNText>そうなのか？　でもユウが『ずばり！』って</JPNText>
    <TransText />
    <SpeakerName>レフィ</SpeakerName>
    <IsNewLine>true</IsNewLine>
    <Notes />
  </DataStruct>
  <DataStruct>
    <counter>18</counter>
    <JPNText>そ、それはいいんですよ</JPNText>
    <TransText />
    <SpeakerName>ユウ</SpeakerName>
    <IsNewLine>false</IsNewLine>
    <Notes />
  </DataStruct>
  <DataStruct>
    <counter>19</counter>
    <JPNText>何誤魔化してるんだよ。ほらっ</JPNText>
    <TransText />
    <SpeakerName>レフィ</SpeakerName>
    <IsNewLine>false</IsNewLine>
    <Notes />
  </DataStruct>
  <DataStruct>
    <counter>20</counter>
    <JPNText>うわぁ～髪をいじるのはやめてくださいよ～</JPNText>
    <TransText />
    <SpeakerName>ユウ</SpeakerName>
    <IsNewLine>true</IsNewLine>
    <Notes />
  </DataStruct>
  <DataStruct>
    <counter>20</counter>
    <JPNText>うわぁ～髪をいじるのはやめてくださいよ～</JPNText>
    <TransText />
    <SpeakerName>ユウ</SpeakerName>
    <IsNewLine>true</IsNewLine>
    <Notes />
  </DataStruct>
  <DataStruct>
    <counter>21</counter>
    <JPNText>そんな答えもあるんですね</JPNText>
    <TransText />
    <SpeakerName>ユウ</SpeakerName>
    <IsNewLine>false</IsNewLine>
    <Notes />
  </DataStruct>
  <DataStruct>
    <counter>22</counter>
    <JPNText>答えって言うか、俺にとって、謎とか、</JPNText>
    <TransText />
    <SpeakerName>レフィ</SpeakerName>
    <IsNewLine>true</IsNewLine>
    <Notes />
  </DataStruct>
  <DataStruct>
    <counter>22</counter>
    <JPNText>答えって言うか、俺にとって、謎とか、</JPNText>
    <TransText />
    <SpeakerName>レフィ</SpeakerName>
    <IsNewLine>true</IsNewLine>
    <Notes />
  </DataStruct>
  <DataStruct>
    <counter>23</counter>
    <JPNText>さすがレフィさん、納得です</JPNText>
    <TransText />
    <SpeakerName>ユウ</SpeakerName>
    <IsNewLine>false</IsNewLine>
    <Notes />
  </DataStruct>
  <DataStruct>
    <counter>24</counter>
    <JPNText>でも、言い得て妙ですね。</JPNText>
    <TransText />
    <SpeakerName>ユウ</SpeakerName>
    <IsNewLine>true</IsNewLine>
    <Notes />
  </DataStruct>
  <DataStruct>
    <counter>24</counter>
    <JPNText>でも、言い得て妙ですね。</JPNText>
    <TransText />
    <SpeakerName>ユウ</SpeakerName>
    <IsNewLine>true</IsNewLine>
    <Notes />
  </DataStruct>
  <DataStruct>
    <counter>25</counter>
    <JPNText>なに、１人で納得してるんだよ…</JPNText>
    <TransText />
    <SpeakerName>レフィ</SpeakerName>
    <IsNewLine>false</IsNewLine>
    <Notes />
  </DataStruct>
  <DataStruct>
    <counter>26</counter>
    <JPNText>メモメモと…謎が謎であるためには</JPNText>
    <TransText />
    <SpeakerName>ユウ</SpeakerName>
    <IsNewLine>true</IsNewLine>
    <Notes />
  </DataStruct>
  <DataStruct>
    <counter>26</counter>
    <JPNText>メモメモと…謎が謎であるためには</JPNText>
    <TransText />
    <SpeakerName>ユウ</SpeakerName>
    <IsNewLine>true</IsNewLine>
    <Notes />
  </DataStruct>
  <DataStruct>
    <counter>27</counter>
    <JPNText>僕のように謎に魅了されている者は、</JPNText>
    <TransText />
    <SpeakerName>ユウ</SpeakerName>
    <IsNewLine>true</IsNewLine>
    <Notes />
  </DataStruct>
  <DataStruct>
    <counter>27</counter>
    <JPNText>僕のように謎に魅了されている者は、</JPNText>
    <TransText />
    <SpeakerName>ユウ</SpeakerName>
    <IsNewLine>true</IsNewLine>
    <Notes />
  </DataStruct>
  <DataStruct>
    <counter>28</counter>
    <JPNText>そうかもしれないな</JPNText>
    <TransText />
    <SpeakerName>レフィ</SpeakerName>
    <IsNewLine>false</IsNewLine>
    <Notes />
  </DataStruct>
  <DataStruct>
    <counter>29</counter>
    <JPNText>最大の謎は、解けない謎…</JPNText>
    <TransText />
    <SpeakerName>ユウ</SpeakerName>
    <IsNewLine>false</IsNewLine>
    <Notes />
  </DataStruct>
  <DataStruct>
    <counter>30</counter>
    <JPNText>考え込むなよ、また頭の糖分が</JPNText>
    <TransText />
    <SpeakerName>レフィ</SpeakerName>
    <IsNewLine>true</IsNewLine>
    <Notes />
  </DataStruct>
  <DataStruct>
    <counter>30</counter>
    <JPNText>考え込むなよ、また頭の糖分が</JPNText>
    <TransText />
    <SpeakerName>レフィ</SpeakerName>
    <IsNewLine>true</IsNewLine>
    <Notes />
  </DataStruct>
  <DataStruct>
    <counter>31</counter>
    <JPNText>最近は、謎が謎を生んでいます…</JPNText>
    <TransText />
    <SpeakerName>ユウ</SpeakerName>
    <IsNewLine>false</IsNewLine>
    <Notes />
  </DataStruct>
  <DataStruct>
    <counter>32</counter>
    <JPNText>謎が謎？</JPNText>
    <TransText />
    <SpeakerName>レフィ</SpeakerName>
    <IsNewLine>false</IsNewLine>
    <Notes />
  </DataStruct>
  <DataStruct>
    <counter>33</counter>
    <JPNText>えぇ、僕に解明できないものは</JPNText>
    <TransText />
    <SpeakerName>ユウ</SpeakerName>
    <IsNewLine>true</IsNewLine>
    <Notes />
  </DataStruct>
  <DataStruct>
    <counter>33</counter>
    <JPNText>えぇ、僕に解明できないものは</JPNText>
    <TransText />
    <SpeakerName>ユウ</SpeakerName>
    <IsNewLine>true</IsNewLine>
    <Notes />
  </DataStruct>
  <DataStruct>
    <counter>34</counter>
    <JPNText>自信失くしたか？</JPNText>
    <TransText />
    <SpeakerName>レフィ</SpeakerName>
    <IsNewLine>false</IsNewLine>
    <Notes />
  </DataStruct>
  <DataStruct>
    <counter>35</counter>
    <JPNText>いいえ。</JPNText>
    <TransText />
    <SpeakerName>ユウ</SpeakerName>
    <IsNewLine>true</IsNewLine>
    <Notes />
  </DataStruct>
  <DataStruct>
    <counter>35</counter>
    <JPNText>いいえ。</JPNText>
    <TransText />
    <SpeakerName>ユウ</SpeakerName>
    <IsNewLine>true</IsNewLine>
    <Notes />
  </DataStruct>
  <DataStruct>
    <counter>36</counter>
    <JPNText>確かにな</JPNText>
    <TransText />
    <SpeakerName>レフィ</SpeakerName>
    <IsNewLine>false</IsNewLine>
    <Notes />
  </DataStruct>
  <DataStruct>
    <counter>37</counter>
    <JPNText>レフィさん、</JPNText>
    <TransText />
    <SpeakerName>ユウ</SpeakerName>
    <IsNewLine>true</IsNewLine>
    <Notes />
  </DataStruct>
  <DataStruct>
    <counter>37</counter>
    <JPNText>レフィさん、</JPNText>
    <TransText />
    <SpeakerName>ユウ</SpeakerName>
    <IsNewLine>true</IsNewLine>
    <Notes />
  </DataStruct>
  <DataStruct>
    <counter>38</counter>
    <JPNText>それは謎がはらむものであり、</JPNText>
    <TransText />
    <SpeakerName>ユウ</SpeakerName>
    <IsNewLine>true</IsNewLine>
    <Notes />
  </DataStruct>
  <DataStruct>
    <counter>38</counter>
    <JPNText>それは謎がはらむものであり、</JPNText>
    <TransText />
    <SpeakerName>ユウ</SpeakerName>
    <IsNewLine>true</IsNewLine>
    <Notes />
  </DataStruct>
  <DataStruct>
    <counter>39</counter>
    <JPNText>俺に聞いてもしかたねーだろ…？</JPNText>
    <TransText />
    <SpeakerName>レフィ</SpeakerName>
    <IsNewLine>false</IsNewLine>
    <Notes />
  </DataStruct>
  <DataStruct>
    <counter>40</counter>
    <JPNText>ズバリ、レフィさんには</JPNText>
    <TransText />
    <SpeakerName>ユウ</SpeakerName>
    <IsNewLine>true</IsNewLine>
    <Notes />
  </DataStruct>
  <DataStruct>
    <counter>40</counter>
    <JPNText>ズバリ、レフィさんには</JPNText>
    <TransText />
    <SpeakerName>ユウ</SpeakerName>
    <IsNewLine>true</IsNewLine>
    <Notes />
  </DataStruct>
  <DataStruct>
    <counter>41</counter>
    <JPNText>なんでだよ…</JPNText>
    <TransText />
    <SpeakerName>レフィ</SpeakerName>
    <IsNewLine>false</IsNewLine>
    <Notes />
  </DataStruct>
  <DataStruct>
    <counter>42</counter>
    <JPNText>謎は多いのです、レフィさん</JPNText>
    <TransText />
    <SpeakerName>ユウ</SpeakerName>
    <IsNewLine>false</IsNewLine>
    <Notes />
  </DataStruct>
  <DataStruct>
    <counter>43</counter>
    <JPNText>まあ、そうだな、次々によく出てくるよな</JPNText>
    <TransText />
    <SpeakerName>レフィ</SpeakerName>
    <IsNewLine>false</IsNewLine>
    <Notes />
  </DataStruct>
  <DataStruct>
    <counter>44</counter>
    <JPNText>１つの謎に足元をすくわれてしまえば、</JPNText>
    <TransText />
    <SpeakerName>ユウ</SpeakerName>
    <IsNewLine>true</IsNewLine>
    <Notes />
  </DataStruct>
  <DataStruct>
    <counter>44</counter>
    <JPNText>１つの謎に足元をすくわれてしまえば、</JPNText>
    <TransText />
    <SpeakerName>ユウ</SpeakerName>
    <IsNewLine>true</IsNewLine>
    <Notes />
  </DataStruct>
  <DataStruct>
    <counter>45</counter>
    <JPNText>お前、もしかして悩んでるのか？</JPNText>
    <TransText />
    <SpeakerName>レフィ</SpeakerName>
    <IsNewLine>false</IsNewLine>
    <Notes />
  </DataStruct>
  <DataStruct>
    <counter>46</counter>
    <JPNText>悩みや、不安はありません</JPNText>
    <TransText />
    <SpeakerName>ユウ</SpeakerName>
    <IsNewLine>false</IsNewLine>
    <Notes />
  </DataStruct>
  <DataStruct>
    <counter>47</counter>
    <JPNText>相変わらず、自信満々だな</JPNText>
    <TransText />
    <SpeakerName>レフィ</SpeakerName>
    <IsNewLine>false</IsNewLine>
    <Notes />
  </DataStruct>
  <DataStruct>
    <counter>48</counter>
    <JPNText>皆さんが、</JPNText>
    <TransText />
    <SpeakerName>ユウ</SpeakerName>
    <IsNewLine>true</IsNewLine>
    <Notes />
  </DataStruct>
  <DataStruct>
    <counter>48</counter>
    <JPNText>皆さんが、</JPNText>
    <TransText />
    <SpeakerName>ユウ</SpeakerName>
    <IsNewLine>true</IsNewLine>
    <Notes />
  </DataStruct>
  <DataStruct>
    <counter>49</counter>
    <JPNText>まっ、そうだな、俺たちは</JPNText>
    <TransText />
    <SpeakerName>レフィ</SpeakerName>
    <IsNewLine>true</IsNewLine>
    <Notes />
  </DataStruct>
  <DataStruct>
    <counter>49</counter>
    <JPNText>まっ、そうだな、俺たちは</JPNText>
    <TransText />
    <SpeakerName>レフィ</SpeakerName>
    <IsNewLine>true</IsNewLine>
    <Notes />
  </DataStruct>
  <DataStruct>
    <counter>50</counter>
    <JPNText>だから、もっと考えてもらわないと</JPNText>
    <TransText />
    <SpeakerName>ユウ</SpeakerName>
    <IsNewLine>true</IsNewLine>
    <Notes />
  </DataStruct>
  <DataStruct>
    <counter>50</counter>
    <JPNText>だから、もっと考えてもらわないと</JPNText>
    <TransText />
    <SpeakerName>ユウ</SpeakerName>
    <IsNewLine>true</IsNewLine>
    <Notes />
  </DataStruct>
  <DataStruct>
    <counter>51</counter>
    <JPNText>なんで俺がやるんだよ…</JPNText>
    <TransText />
    <SpeakerName>レフィ</SpeakerName>
    <IsNewLine>false</IsNewLine>
    <Notes />
  </DataStruct>
  <DataStruct>
    <counter>52</counter>
    <JPNText>人ですか？</JPNText>
    <TransText />
    <SpeakerName>ユウ</SpeakerName>
    <IsNewLine>false</IsNewLine>
    <Notes />
  </DataStruct>
  <DataStruct>
    <counter>53</counter>
    <JPNText>だいたい犯人がいるだろ</JPNText>
    <TransText />
    <SpeakerName>レフィ</SpeakerName>
    <IsNewLine>false</IsNewLine>
    <Notes />
  </DataStruct>
  <DataStruct>
    <counter>54</counter>
    <JPNText>相変わらず、何も考えていませんね</JPNText>
    <TransText />
    <SpeakerName>ユウ</SpeakerName>
    <IsNewLine>true</IsNewLine>
    <Notes />
  </DataStruct>
  <DataStruct>
    <counter>54</counter>
    <JPNText>相変わらず、何も考えていませんね</JPNText>
    <TransText />
    <SpeakerName>ユウ</SpeakerName>
    <IsNewLine>true</IsNewLine>
    <Notes />
  </DataStruct>
  <DataStruct>
    <counter>55</counter>
    <JPNText>なるほど、そういうことなんですね！</JPNText>
    <TransText />
    <SpeakerName>ユウ</SpeakerName>
    <IsNewLine>true</IsNewLine>
    <Notes />
  </DataStruct>
  <DataStruct>
    <counter>55</counter>
    <JPNText>なるほど、そういうことなんですね！</JPNText>
    <TransText />
    <SpeakerName>ユウ</SpeakerName>
    <IsNewLine>true</IsNewLine>
    <Notes />
  </DataStruct>
  <DataStruct>
    <counter>56</counter>
    <JPNText>なにやばい顔してんだよ…</JPNText>
    <TransText />
    <SpeakerName>レフィ</SpeakerName>
    <IsNewLine>false</IsNewLine>
    <Notes />
  </DataStruct>
  <DataStruct>
    <counter>57</counter>
    <JPNText>フフフ…謎を感じるのも人間、</JPNText>
    <TransText />
    <SpeakerName>ユウ</SpeakerName>
    <IsNewLine>true</IsNewLine>
    <Notes />
  </DataStruct>
  <DataStruct>
    <counter>57</counter>
    <JPNText>フフフ…謎を感じるのも人間、</JPNText>
    <TransText />
    <SpeakerName>ユウ</SpeakerName>
    <IsNewLine>true</IsNewLine>
    <Notes />
  </DataStruct>
  <DataStruct>
    <counter>58</counter>
    <JPNText>人の繋がりが無限に謎を</JPNText>
    <TransText />
    <SpeakerName>ユウ</SpeakerName>
    <IsNewLine>true</IsNewLine>
    <Notes />
  </DataStruct>
  <DataStruct>
    <counter>58</counter>
    <JPNText>人の繋がりが無限に謎を</JPNText>
    <TransText />
    <SpeakerName>ユウ</SpeakerName>
    <IsNewLine>true</IsNewLine>
    <Notes />
  </DataStruct>
  <DataStruct>
    <counter>59</counter>
    <JPNText>はあ…？</JPNText>
    <TransText />
    <SpeakerName>レフィ</SpeakerName>
    <IsNewLine>false</IsNewLine>
    <Notes />
  </DataStruct>
  <DataStruct>
    <counter>60</counter>
    <JPNText>いやレフィさん、あなたの存在は</JPNText>
    <TransText />
    <SpeakerName>ユウ</SpeakerName>
    <IsNewLine>true</IsNewLine>
    <Notes />
  </DataStruct>
  <DataStruct>
    <counter>60</counter>
    <JPNText>いやレフィさん、あなたの存在は</JPNText>
    <TransText />
    <SpeakerName>ユウ</SpeakerName>
    <IsNewLine>true</IsNewLine>
    <Notes />
  </DataStruct>
  <DataStruct>
    <counter>61</counter>
    <JPNText>俺はチョコクッキーかよ…</JPNText>
    <TransText />
    <SpeakerName>レフィ</SpeakerName>
    <IsNewLine>false</IsNewLine>
    <Notes />
  </DataStruct>
  <DataStruct>
    <counter>62</counter>
    <JPNText>ゆえに真実もまた、人の繋がりが創り出す</JPNText>
    <TransText />
    <SpeakerName>ユウ</SpeakerName>
    <IsNewLine>true</IsNewLine>
    <Notes />
  </DataStruct>
  <DataStruct>
    <counter>62</counter>
    <JPNText>ゆえに真実もまた、人の繋がりが創り出す</JPNText>
    <TransText />
    <SpeakerName>ユウ</SpeakerName>
    <IsNewLine>true</IsNewLine>
    <Notes />
  </DataStruct>
  <DataStruct>
    <counter>63</counter>
    <JPNText>だったら、謎が１つ解けたじゃないか</JPNText>
    <TransText />
    <SpeakerName>レフィ</SpeakerName>
    <IsNewLine>false</IsNewLine>
    <Notes />
  </DataStruct>
  <DataStruct>
    <counter>64</counter>
    <JPNText>え、何のことです？</JPNText>
    <TransText />
    <SpeakerName>ユウ</SpeakerName>
    <IsNewLine>false</IsNewLine>
    <Notes />
  </DataStruct>
  <DataStruct>
    <counter>65</counter>
    <JPNText>俺たちが一緒に戦っている理由だ</JPNText>
    <TransText />
    <SpeakerName>レフィ</SpeakerName>
    <IsNewLine>false</IsNewLine>
    <Notes />
  </DataStruct>
  <DataStruct>
    <counter>66</counter>
    <JPNText>レフィさん…</JPNText>
    <TransText />
    <SpeakerName>ユウ</SpeakerName>
    <IsNewLine>false</IsNewLine>
    <Notes />
  </DataStruct>
  <DataStruct>
    <counter>67</counter>
    <JPNText>さ、謎が解けたご褒美だ。</JPNText>
    <TransText />
    <SpeakerName>レフィ</SpeakerName>
    <IsNewLine>true</IsNewLine>
    <Notes />
  </DataStruct>
  <DataStruct>
    <counter>67</counter>
    <JPNText>さ、謎が解けたご褒美だ。</JPNText>
    <TransText />
    <SpeakerName>レフィ</SpeakerName>
    <IsNewLine>true</IsNewLine>
    <Notes />
  </DataStruct>
  <DataStruct>
    <counter>68</counter>
    <JPNText>…簡単ですよ、両手でしょ</JPNText>
    <TransText />
    <SpeakerName>ユウ</SpeakerName>
    <IsNewLine>false</IsNewLine>
    <Notes />
  </DataStruct>
  <DataStruct>
    <counter>69</counter>
    <JPNText>理由は？</JPNText>
    <TransText />
    <SpeakerName>レフィ</SpeakerName>
    <IsNewLine>false</IsNewLine>
    <Notes />
  </DataStruct>
  <DataStruct>
    <counter>70</counter>
    <JPNText>あなたが僕にクッキーを</JPNText>
    <TransText />
    <SpeakerName>ユウ</SpeakerName>
    <IsNewLine>true</IsNewLine>
    <Notes />
  </DataStruct>
  <DataStruct>
    <counter>70</counter>
    <JPNText>あなたが僕にクッキーを</JPNText>
    <TransText />
    <SpeakerName>ユウ</SpeakerName>
    <IsNewLine>true</IsNewLine>
    <Notes />
  </DataStruct>
  <DataStruct>
    <counter>71</counter>
    <JPNText>なるほどな。正解だ</JPNText>
    <TransText />
    <SpeakerName>レフィ</SpeakerName>
    <IsNewLine>false</IsNewLine>
    <Notes />
  </DataStruct>
  <DataStruct>
    <counter>72</counter>
    <JPNText>フフフ、あなたは、</JPNText>
    <TransText />
    <SpeakerName>ユウ</SpeakerName>
    <IsNewLine>true</IsNewLine>
    <Notes />
  </DataStruct>
  <DataStruct>
    <counter>72</counter>
    <JPNText>フフフ、あなたは、</JPNText>
    <TransText />
    <SpeakerName>ユウ</SpeakerName>
    <IsNewLine>true</IsNewLine>
    <Notes />
  </DataStruct>
  <DataStruct>
    <counter>73</counter>
    <JPNText>俺が？</JPNText>
    <TransText />
    <SpeakerName>レフィ</SpeakerName>
    <IsNewLine>false</IsNewLine>
    <Notes />
  </DataStruct>
  <DataStruct>
    <counter>74</counter>
    <JPNText>えぇ、名探偵に助手はかかせませんから。</JPNText>
    <TransText />
    <SpeakerName>ユウ</SpeakerName>
    <IsNewLine>true</IsNewLine>
    <Notes />
  </DataStruct>
  <DataStruct>
    <counter>74</counter>
    <JPNText>えぇ、名探偵に助手はかかせませんから。</JPNText>
    <TransText />
    <SpeakerName>ユウ</SpeakerName>
    <IsNewLine>true</IsNewLine>
    <Notes />
  </DataStruct>
  <DataStruct>
    <counter>75</counter>
    <JPNText>いつでもどこでも、</JPNText>
    <TransText />
    <SpeakerName>ユウ</SpeakerName>
    <IsNewLine>true</IsNewLine>
    <Notes />
  </DataStruct>
  <DataStruct>
    <counter>75</counter>
    <JPNText>いつでもどこでも、</JPNText>
    <TransText />
    <SpeakerName>ユウ</SpeakerName>
    <IsNewLine>true</IsNewLine>
    <Notes />
  </DataStruct>
  <DataStruct>
    <counter>76</counter>
    <JPNText>なんだそりゃ</JPNText>
    <TransText />
    <SpeakerName>レフィ</SpeakerName>
    <IsNewLine>false</IsNewLine>
    <Notes />
  </DataStruct>
  <DataStruct>
    <counter>77</counter>
    <JPNText>これ、探偵士助手のピンバッジです。</JPNText>
    <TransText />
    <SpeakerName>ユウ</SpeakerName>
    <IsNewLine>true</IsNewLine>
    <Notes />
  </DataStruct>
  <DataStruct>
    <counter>77</counter>
    <JPNText>これ、探偵士助手のピンバッジです。</JPNText>
    <TransText />
    <SpeakerName>ユウ</SpeakerName>
    <IsNewLine>true</IsNewLine>
    <Notes />
  </DataStruct>
</ArrayOfDataStruct>